{
    "fluentMethods": true,
    "relationships": [
        {
            "relationshipName": "game",
            "otherEntityName": "game",
            "relationshipType": "many-to-one",
            "otherEntityField": "description"
        },
        {
            "relationshipName": "template",
            "otherEntityName": "matchTemplate",
            "relationshipType": "many-to-one",
            "otherEntityField": "description"
        },
        {
            "relationshipName": "attempts",
            "otherEntityName": "attempt",
            "relationshipType": "one-to-many",
            "otherEntityRelationshipName": "match"
        },
        {
            "relationshipName": "session",
            "otherEntityName": "session",
            "relationshipType": "many-to-one",
            "otherEntityField": "id"
        }
    ],
    "fields": [
        {
            "fieldName": "start",
            "fieldType": "ZonedDateTime"
        },
        {
            "fieldName": "stop",
            "fieldType": "ZonedDateTime"
        },
        {
            "fieldName": "diffLevel",
            "fieldType": "Long"
        },
        {
            "fieldName": "userId",
            "fieldType": "String"
        },
        {
            "fieldName": "lastStart",
            "fieldType": "ZonedDateTime"
        },
        {
            "fieldName": "timeSpent",
            "fieldType": "Long"
        },
        {
            "fieldName": "usedToPO",
            "fieldType": "Boolean"
        },
        {
            "fieldName": "elaborated",
            "fieldType": "Boolean"
        },
        {
            "fieldName": "matchToken",
            "fieldType": "Long"
        },
        {
            "fieldName": "valid",
            "fieldType": "Boolean"
        },
        {
            "fieldName": "sendToPo",
            "fieldType": "Boolean"
        },
        {
            "fieldName": "retry",
            "fieldType": "Long"
        },
        {
            "fieldName": "anomalous",
            "fieldType": "Boolean"
        },
        {
            "fieldName": "replayState",
            "fieldType": "MatchReplayState",
            "fieldValues": "playing,main,old,cloned"
        }
    ],
    "changelogDate": "20170627083527",
    "dto": "no",
    "service": "serviceImpl",
    "entityTableName": "match",
    "pagination": "pager"
}
